{
  "@context" : "http://www.w3.org/ns/csvw",
  "@type" : "TableGroup",
  "tables" : [ {
    "@type" : "Table",
    "url" : "MissingDataExample.ttl0.csv",
    "tableSchema" : {
      "@type" : "Schema",
      "columns" : [ {
        "@type" : "Column",
        "titles" : "Subject",
        "name" : "Subject",
        "valueUrl" : "{+Subject}",
        "suppressOutput" : true
      }, {
        "@type" : "Column",
        "titles" : "type",
        "name" : "type",
        "propertyUrl" : "http://www.w3.org/1999/02/22-rdf-syntax-ns#type",
        "valueUrl" : "http://purl.org/linked-data/cube#{+type}",
        "aboutUrl" : "{+Subject}"
      }, {
        "@type" : "Column",
        "titles" : "dataSet",
        "name" : "dataSet",
        "propertyUrl" : "http://purl.org/linked-data/cube#dataSet",
        "valueUrl" : "https://data.cssz.cz/resource/dataset/{+dataSet}",
        "aboutUrl" : "{+Subject}"
      }, {
        "@type" : "Column",
        "titles" : "rok",
        "name" : "rok",
        "propertyUrl" : "https://data.cssz.cz/ontology/dimension/rok",
        "valueUrl" : "https://data.cssz.cz/resource/reference.data.gov.uk/id/gregorian-year/{+rok}",
        "aboutUrl" : "{+Subject}"
      }, {
        "@type" : "Column",
        "titles" : "measureType",
        "name" : "measureType",
        "propertyUrl" : "http://purl.org/linked-data/cube#measureType",
        "valueUrl" : "https://data.cssz.cz/ontology/measure/{+measureType}",
        "aboutUrl" : "{+Subject}"
      }, {
        "@type" : "Column",
        "titles" : "prumerny-plat-cssz",
        "name" : "prumernyplatcssz",
        "propertyUrl" : "https://data.cssz.cz/ontology/measure/prumerny-plat-cssz",
        "datatype" : "integer",
        "aboutUrl" : "{+Subject}"
      }, {
        "@type" : "Column",
        "titles" : "median",
        "name" : "median",
        "propertyUrl" : "https://data.cssz.cz/ontology/measure/median",
        "datatype" : "integer",
        "aboutUrl" : "{+Subject}"
      }, {
        "@type" : "Column",
        "titles" : "Title (cs)",
        "name" : "title_cs",
        "propertyUrl" : "http://purl.org/dc/terms/title",
        "aboutUrl" : "https://data.cssz.cz/resource/dataset/{+Subject}",
        "lang" : "cs"
      }, {
        "@type" : "Column",
        "titles" : "label (cs)",
        "name" : "label_cs",
        "propertyUrl" : "http://www.w3.org/2000/01/rdf-schema#label",
        "aboutUrl" : "{+Subject}",
        "lang" : "cs"
      }, {
        "@type" : "Column",
        "titles" : "Description (cs)",
        "name" : "description_cs",
        "propertyUrl" : "http://purl.org/dc/terms/description",
        "aboutUrl" : "https://data.cssz.cz/resource/dataset/{+Subject}",
        "lang" : "cs"
      }, {
        "@type" : "Column",
        "titles" : "comment (cs)",
        "name" : "comment_cs",
        "propertyUrl" : "http://www.w3.org/2000/01/rdf-schema#comment",
        "aboutUrl" : "https://data.cssz.cz/resource/dataset/{+Subject}",
        "lang" : "cs"
      }, {
        "@type" : "Column",
        "titles" : "Publisher",
        "name" : "publisher",
        "propertyUrl" : "http://purl.org/dc/terms/publisher",
        "valueUrl" : "http://{+publisher}",
        "aboutUrl" : "https://data.cssz.cz/resource/dataset/{+Subject}"
      }, {
        "@type" : "Column",
        "titles" : "structure",
        "name" : "structure",
        "propertyUrl" : "http://purl.org/linked-data/cube#structure",
        "valueUrl" : "https://data.cssz.cz/resource/data-structure-definition/{+structure}",
        "aboutUrl" : "https://data.cssz.cz/resource/dataset/{+Subject}"
      }, {
        "@type" : "Column",
        "titles" : "component",
        "name" : "component",
        "propertyUrl" : "http://purl.org/linked-data/cube#component",
        "valueUrl" : "https://blank_Nodes_IRI.org/{+component}",
        "aboutUrl" : "https://data.cssz.cz/resource/data-structure-definition/{+Subject}",
        "separator" : ","
      }, {
        "@type" : "Column",
        "titles" : "dimension",
        "name" : "dimension",
        "propertyUrl" : "http://purl.org/linked-data/cube#dimension",
        "valueUrl" : "https://data.cssz.cz/ontology/dimension/{+dimension}"
      }, {
        "@type" : "Column",
        "titles" : "order",
        "name" : "order",
        "propertyUrl" : "http://purl.org/linked-data/cube#order",
        "datatype" : "integer"
      }, {
        "@type" : "Column",
        "titles" : "measure",
        "name" : "measure",
        "propertyUrl" : "http://purl.org/linked-data/cube#measure",
        "valueUrl" : "https://data.cssz.cz/ontology/measure/{+measure}"
      }, {
        "@type" : "Column",
        "propertyUrl" : "rdf:type",
        "valueUrl" : "{+type}",
        "aboutUrl" : "{+Observation}",
        "virtual" : true
      } ],
      "primaryKey" : "Subject",
      "rowTitles" : [ "Subject", "type", "dataSet", "rok", "measureType", "prumernyplatcssz", "median", "title_cs", "label_cs", "description_cs", "comment_cs", "publisher", "structure", "component", "dimension", "order", "measure" ]
    },
    "transformations" : [ {
      "@type" : "Template",
      "url" : "https://raw.githubusercontent.com/LadyMalande/RDFtoCSVNotes/main/scripts/transformationForBlankNodesStreamed.js",
      "scriptFormat" : "http://www.iana.org/assignments/media-types/application/javascript",
      "targetFormat" : "http://www.iana.org/assignments/media-types/turtle",
      "source" : "rdf",
      "titles" : "RDF format used as the output format in the transformation from CSV to RDF"
    } ]
  } ]
}